{"State.6b5ac7ff-6000-4c8c-b4ed-27629ea1c9d0": {"id": "6b5ac7ff-6000-4c8c-b4ed-27629ea1c9d0", "created_at": "2022-12-05T17:41:05.687678", "updated_at": "2022-12-05T17:41:05.687685", "name": "\"California\"", "__class__": "State"}, "State.6334fbcb-76e7-4e68-b5b5-c733348b559c": {"id": "6334fbcb-76e7-4e68-b5b5-c733348b559c", "created_at": "2022-12-05T17:41:05.689708", "updated_at": "2022-12-05T17:41:05.689735", "name": "\"Arizona\"", "__class__": "State"}, "Place.a56ca40b-42f4-4e67-bee0-e3589f2c904f": {"id": "a56ca40b-42f4-4e67-bee0-e3589f2c904f", "created_at": "2022-12-05T17:41:05.692656", "updated_at": "2022-12-05T17:41:05.692665", "city_id": "\"0001\"", "user_id": "\"0001\"", "name": "\"My little house\"", "number_rooms": 4, "number_bathrooms": 2, "max_guest": 10, "price_by_night": 300, "latitude": 37.773972, "longitude": -122.431297, "__class__": "Place"}}